rfsdk/__init__.py
rfsdk/comm_utils.py
rfsdk/condition_client.py
rfsdk/gateway.py
rfsdk/quote_client.py
rfsdk/trade_client.py
rfsdk/ant/__init__.py
rfsdk/ant/logger.py
rfsdk/ant/pyant.cp38-win_amd64.pyd
rfsdk/ant/rpc_call_helper.py
rfsdk/conf/instrument.json
rfsdk/conf/station.json
rfsdk/protocol/__init__.py
rfsdk/protocol/common_pb2.py
rfsdk/protocol/service_method.py
rfsdk/protocol/account/__init__.py
rfsdk/protocol/account/account_req_helper.py
rfsdk/protocol/condition/__init__.py
rfsdk/protocol/condition/condition_futures_pb2.py
rfsdk/protocol/condition/condition_req_helper.py
rfsdk/protocol/condition/condition_stock_pb2.py
rfsdk/protocol/condition/nest_condition_futures_pb2.py
rfsdk/protocol/quote/__init__.py
rfsdk/protocol/quote/mdsquote_pb2.py
rfsdk/protocol/quote/quote_enum_pb2.py
rfsdk/protocol/quote/quote_pb2.py
rfsdk/protocol/quote/quote_req_helper.py
rfsdk/protocol/trade/__init__.py
rfsdk/protocol/trade/trade_enum_pb2.py
rfsdk/protocol/trade/trade_futures_pb2.py
rfsdk/protocol/trade/trade_pb2.py
rfsdk/protocol/trade/trade_req_helper.py
rfsdk/protocol/trade/trade_stock_pb2.py
rfsdk-0.4.6.dist-info/LICENSE
rfsdk-0.4.6.dist-info/METADATA
rfsdk-0.4.6.dist-info/WHEEL
rfsdk-0.4.6.dist-info/top_level.txt
rfsdk-0.4.6.dist-info/RECORD
