Metadata-Version: 2.1
Name: rfsdk
Version: 0.4.6
Summary: No description.
Home-page: UNKNOWN
Author: loufu
Author-email: loufu.2004@163.com
License: UNKNOWN
Platform: UNKNOWN
Classifier: Programming Language :: Python :: 3.8
Classifier: License :: OSI Approved :: MIT License
Classifier: Operating System :: Microsoft :: Windows :: Windows 7
Requires-Dist: protobuf
